odoo/addons/ebill_paynet/README.rst
odoo/addons/ebill_paynet/__init__.py
odoo/addons/ebill_paynet/__manifest__.py
odoo/addons/ebill_paynet/components/__init__.py
odoo/addons/ebill_paynet/components/api.py
odoo/addons/ebill_paynet/components/certificats/prod_services_chain.pem
odoo/addons/ebill_paynet/components/certificats/test_services_chain.pem
odoo/addons/ebill_paynet/components/wsdl/DWSPayNet.wsdl
odoo/addons/ebill_paynet/components/wsdl/DXPPShipmentExchangePayNet.xsd
odoo/addons/ebill_paynet/components/wsdl/DXPPTypesPayNet.xsd
odoo/addons/ebill_paynet/data/ir_cron.xml
odoo/addons/ebill_paynet/data/mail_activity_type.xml
odoo/addons/ebill_paynet/data/transmit.method.xml
odoo/addons/ebill_paynet/i18n/de.po
odoo/addons/ebill_paynet/i18n/ebill_paynet.pot
odoo/addons/ebill_paynet/i18n/fr.po
odoo/addons/ebill_paynet/messages/invoice-2003A.jinja
odoo/addons/ebill_paynet/messages/invoice-2013A.jinja
odoo/addons/ebill_paynet/models/__init__.py
odoo/addons/ebill_paynet/models/account_invoice.py
odoo/addons/ebill_paynet/models/ebill_payment_contract.py
odoo/addons/ebill_paynet/models/paynet_invoice_message.py
odoo/addons/ebill_paynet/models/paynet_service.py
odoo/addons/ebill_paynet/models/sale_order.py
odoo/addons/ebill_paynet/readme/CONFIGURE.rst
odoo/addons/ebill_paynet/readme/CONTRIBUTORS.rst
odoo/addons/ebill_paynet/readme/CREDITS.rst
odoo/addons/ebill_paynet/readme/DESCRIPTION.rst
odoo/addons/ebill_paynet/readme/INSTALL.rst
odoo/addons/ebill_paynet/readme/ROADMAP.rst
odoo/addons/ebill_paynet/readme/USAGE.rst
odoo/addons/ebill_paynet/security/ir.model.access.csv
odoo/addons/ebill_paynet/static/description/icon.png
odoo/addons/ebill_paynet/static/description/index.html
odoo/addons/ebill_paynet/tests/__init__.py
odoo/addons/ebill_paynet/tests/common.py
odoo/addons/ebill_paynet/tests/test_ebill_paynet.py
odoo/addons/ebill_paynet/tests/test_invoice_message.py
odoo/addons/ebill_paynet/tests/test_invoice_message_b2b.py
odoo/addons/ebill_paynet/tests/examples/invoice_1.xml
odoo14_addon_ebill_paynet-14.0.1.1.4.dist-info/METADATA
odoo14_addon_ebill_paynet-14.0.1.1.4.dist-info/WHEEL
odoo14_addon_ebill_paynet-14.0.1.1.4.dist-info/top_level.txt
odoo14_addon_ebill_paynet-14.0.1.1.4.dist-info/RECORD
