Metadata-Version: 2.1
Name: odoo14-addon-ebill-paynet
Version: 14.0.1.1.4
Summary: Paynet platform bridge implementation
Home-page: https://github.com/OCA/l10n-switzerland
Author: Camptocamp SA,Odoo Community Association (OCA)
Author-email: support@odoo-community.org
License: AGPL-3
Platform: UNKNOWN
Classifier: Programming Language :: Python
Classifier: Framework :: Odoo
Classifier: Framework :: Odoo :: 14.0
Classifier: License :: OSI Approved :: GNU Affero General Public License v3
Requires-Python: >=3.6
Requires-Dist: odoo14-addon-account-invoice-export
Requires-Dist: odoo14-addon-base-ebill-payment-contract
Requires-Dist: odoo14-addon-l10n-ch-base-bank
Requires-Dist: odoo14-addon-queue-job
Requires-Dist: odoo <14.1dev,>=14.0a
Requires-Dist: zeep
